vklight/__init__.py
vklight/core.py
vklight-1.3.8.dist-info/WHEEL
vklight-1.3.8.dist-info/METADATA
vklight-1.3.8.dist-info/RECORD
