Metadata-Version: 2.1
Name: vklight
Version: 1.3.8
Summary: VKLight - Light wrapper for VK's API
Author: Ivan
Requires-Python: >=3.8,<4.0
Classifier: Programming Language :: Python :: 3
Classifier: Programming Language :: Python :: 3.8
Requires-Dist: requests (>=2.24.0,<3.0.0)
